nmk_doc/__init__.py
nmk_doc/badges.yml
nmk_doc/builders.py
nmk_doc/doc.yml
nmk_doc/plugin.yml
nmk_doc/resolvers.py
nmk_doc/templates/__init__.py
nmk_doc/templates/config.py.jinja
nmk_doc/templates/readthedocs.yaml.jinja
nmk_doc-1.0.2.dist-info/LICENSE
nmk_doc-1.0.2.dist-info/METADATA
nmk_doc-1.0.2.dist-info/WHEEL
nmk_doc-1.0.2.dist-info/top_level.txt
nmk_doc-1.0.2.dist-info/RECORD
