Metadata-Version: 2.1
Name: nmk-doc
Version: 1.0.2
Summary: Documentation handling plugin for nmk build system
Author: The dynod project
Maintainer: The dynod project
License: MIT License
Project-URL: Homepage, https://github.com/dynod/nmk-doc
Project-URL: Repository, https://github.com/dynod/nmk-doc
Project-URL: Issues, https://github.com/dynod/nmk/issues?q=is%3Aopen+is%3Aissue+label%3Aplugin%3Adoc
Classifier: Programming Language :: Python :: 3.9
Classifier: Programming Language :: Python :: 3.10
Classifier: Programming Language :: Python :: 3.11
Classifier: Programming Language :: Python :: 3.12
Classifier: Programming Language :: Python :: 3.13
Requires-Python: >=3.9
License-File: LICENSE
Requires-Dist: nmk-base
Requires-Dist: sphinx
Requires-Dist: sphinx_rtd_theme
Requires-Dist: myst-parser
